pyrallel/__init__.py
pyrallel/__version__.py
pyrallel/map_reduce.py
pyrallel/parallel_processor.py
pyrallel/paralleller.py
pyrallel/queue.py
pyrallel/tests/__init__.py
pyrallel/tests/test_map_reduce.py
pyrallel/tests/test_parallel_processor.py
pyrallel/tests/test_queue.py
pyrallel.lib-0.0.10.dist-info/LICENSE
pyrallel.lib-0.0.10.dist-info/METADATA
pyrallel.lib-0.0.10.dist-info/WHEEL
pyrallel.lib-0.0.10.dist-info/top_level.txt
pyrallel.lib-0.0.10.dist-info/RECORD
