Metadata-Version: 2.1
Name: pyrallel.lib
Version: 0.0.10
Summary: Yet another easy-to-use python3 parallel library for humans.
Home-page: https://github.com/usc-isi-i2/pyrallel
Author: USC/ISI
Author-email: yixiangy@isi.edu
License: MIT
Project-URL: Bug Tracker, https://github.com/usc-isi-i2/pyrallel/issues
Project-URL: Documentation, https://pyrallel.readthedocs.io
Project-URL: Source Code, https://github.com/usc-isi-i2/pyrallel
Platform: UNKNOWN
Classifier: Programming Language :: Python :: 3
Classifier: Natural Language :: English
Classifier: License :: OSI Approved :: MIT License
Classifier: Operating System :: OS Independent
Classifier: Topic :: Software Development :: Libraries
Classifier: Topic :: Software Development :: Libraries :: Python Modules
